gmm_mi/__init__.py
gmm_mi/cross_validation.py
gmm_mi/gmm.py
gmm_mi/initializations.py
gmm_mi/mi.py
gmm_mi/param_holders.py
gmm_mi/single_fit.py
gmm_mi/data/__init__.py
gmm_mi/data/synthetic_data.py
gmm_mi/utils/__init__.py
gmm_mi/utils/analytic_MI.py
gmm_mi/utils/plotting.py
gmm_mi/utils/transformations.py
gmm_mi-0.8.2.dist-info/licenses/LICENSE.txt
gmm_mi-0.8.2.dist-info/licenses/LICENSE_EXT.txt
notebooks/__init__.py
gmm_mi-0.8.2.dist-info/METADATA
gmm_mi-0.8.2.dist-info/WHEEL
gmm_mi-0.8.2.dist-info/top_level.txt
gmm_mi-0.8.2.dist-info/RECORD
