Metadata-Version: 2.4
Name: gmm_mi
Version: 0.8.2
Summary: Estimate mutual information distribution with Gaussian mixture models
Home-page: https://github.com/dpiras/GMM-MI
Author: Davide Piras
Author-email: dr.davide.piras@gmail.com
License: GNU General Public License v3.0 (GPLv3)
Classifier: Programming Language :: Python :: 3
Classifier: License :: OSI Approved :: GNU General Public License v3 (GPLv3)
Classifier: Operating System :: OS Independent
Requires-Python: >=3.8
License-File: LICENSE.txt
License-File: LICENSE_EXT.txt
Requires-Dist: pytest
Requires-Dist: tqdm
Requires-Dist: matplotlib>=3.1.2
Requires-Dist: numpy>=1.17.4
Requires-Dist: scikit-learn>=1.0.2
Requires-Dist: scipy>=1.7.1
Requires-Dist: chainconsumer<=0.34.0
Dynamic: author
Dynamic: author-email
Dynamic: classifier
Dynamic: description
Dynamic: description-content-type
Dynamic: home-page
Dynamic: license
Dynamic: license-file
Dynamic: requires-dist
Dynamic: requires-python
Dynamic: summary
